intacctsdk/__init__.py
intacctsdk/constants.py
intacctsdk/enums.py
intacctsdk/exceptions.py
intacctsdk/intacctsdk.py
intacctsdk/apis/__init__.py
intacctsdk/apis/accounts.py
intacctsdk/apis/allocations.py
intacctsdk/apis/ap_payments.py
intacctsdk/apis/api_base.py
intacctsdk/apis/attachment_folders.py
intacctsdk/apis/attachments.py
intacctsdk/apis/bills.py
intacctsdk/apis/charge_card_accounts.py
intacctsdk/apis/charge_card_transactions.py
intacctsdk/apis/checking_accounts.py
intacctsdk/apis/classes.py
intacctsdk/apis/contacts.py
intacctsdk/apis/cost_types.py
intacctsdk/apis/customers.py
intacctsdk/apis/departments.py
intacctsdk/apis/dimensions.py
intacctsdk/apis/employees.py
intacctsdk/apis/expense_payment_types.py
intacctsdk/apis/expense_reports.py
intacctsdk/apis/expense_types.py
intacctsdk/apis/items.py
intacctsdk/apis/journal_entries.py
intacctsdk/apis/location_entities.py
intacctsdk/apis/locations.py
intacctsdk/apis/projects.py
intacctsdk/apis/savings_accounts.py
intacctsdk/apis/sessions.py
intacctsdk/apis/tasks.py
intacctsdk/apis/tax_details.py
intacctsdk/apis/vendors.py
sageintacctrestsdk-1.4.3.dist-info/licenses/LICENSE
sageintacctrestsdk-1.4.3.dist-info/METADATA
sageintacctrestsdk-1.4.3.dist-info/WHEEL
sageintacctrestsdk-1.4.3.dist-info/top_level.txt
sageintacctrestsdk-1.4.3.dist-info/RECORD
