Metadata-Version: 2.4
Name: sageintacctrestsdk
Version: 1.4.3
Summary: Python SDK for accessing Sage Intacct REST APIs
Home-page: https://github.com/fylein/intacct-rest-sdk-py
Author: Ashwin T
Author-email: ashwin.t@fyle.in
License: MIT
Keywords: sage-intacct,sage,rest-api,api,python,sdk
Classifier: Topic :: Internet :: WWW/HTTP
Classifier: Intended Audience :: Developers
Classifier: Programming Language :: Python :: 3
Classifier: License :: OSI Approved :: MIT License
Classifier: Operating System :: OS Independent
License-File: LICENSE
Requires-Dist: requests>=2.31.0
Dynamic: author
Dynamic: author-email
Dynamic: classifier
Dynamic: description
Dynamic: description-content-type
Dynamic: home-page
Dynamic: keywords
Dynamic: license
Dynamic: license-file
Dynamic: requires-dist
Dynamic: summary
